odoo/addons/suno/__init__.py
odoo/addons/suno/__manifest__.py
odoo/addons/suno/i18n/ca_ES.po
odoo/addons/suno/i18n/es.po
odoo/addons/suno/migrations/12.0.0.0.2/post-adjust-price-hour-cost.py
odoo/addons/suno/report/__init__.py
odoo/addons/suno/report/project_profitability_report_analysis.py
odoo/addons/suno/views/project_profitability_report_analysis_views.xml
odoo12_addon_suno-12.0.0.0.2.dist-info/METADATA
odoo12_addon_suno-12.0.0.0.2.dist-info/WHEEL
odoo12_addon_suno-12.0.0.0.2.dist-info/top_level.txt
odoo12_addon_suno-12.0.0.0.2.dist-info/RECORD
